bbx/VERSION
bbx/__init__.py
bbx/boxes.py
bbx/ops.py
bbx-1.1.2.dist-info/AUTHORS
bbx-1.1.2.dist-info/LICENSE
bbx-1.1.2.dist-info/METADATA
bbx-1.1.2.dist-info/WHEEL
bbx-1.1.2.dist-info/top_level.txt
bbx-1.1.2.dist-info/RECORD
