Metadata-Version: 2.1
Name: bbx
Version: 1.1.2
Summary: Simple bounding box operations
Home-page: https://github.com/RomanJuranek/bbx
Author: Roman Juranek
Author-email: rjuranek1983@gmail.com
License: UNKNOWN
Project-URL: Source, https://github.com/RomanJuranek/bbx
Keywords: bounding box,non maxima suppression
Platform: UNKNOWN
Classifier: Development Status :: 4 - Beta
Classifier: License :: OSI Approved :: MIT License
Classifier: Programming Language :: Python :: 3
Requires-Python: >=3.6
Requires-Dist: numpy
